ceasium/.gitignore
ceasium/__init__.py
ceasium/constants.py
ceasium/main.py
ceasium/requirements.txt
ceasium-0.16.0.dist-info/METADATA
ceasium-0.16.0.dist-info/WHEEL
ceasium-0.16.0.dist-info/entry_points.txt
ceasium-0.16.0.dist-info/RECORD
